{
  "book": "VI",
  "slug": "book-vi",
  "title": "Categorical Life",
  "total_objects": 217,
  "types": {
    "remark": 30,
    "definition": 92,
    "proposition": 24,
    "lemma": 17,
    "theorem": 54
  },
  "scopes": {
    "established": 21,
    "tau-effective": 190,
    "conjectural": 5,
    "metaphorical": 1
  },
  "formalizations": {
    "not_applicable": 31,
    "planned": 143,
    "not_formalized": 43
  },
  "top_central": [
    {
      "id": "VI.D04",
      "name": "\u03c4-Distinction",
      "rev_dep_count": 23
    },
    {
      "id": "VI.D08",
      "name": "SelfDesc Predicate",
      "rev_dep_count": 19
    },
    {
      "id": "VI.D10",
      "name": "Life Loop Class",
      "rev_dep_count": 13
    },
    {
      "id": "VI.T05",
      "name": "Metabolic Fiber Theorem",
      "rev_dep_count": 8
    },
    {
      "id": "VI.T01",
      "name": "Parity Bridge Theorem",
      "rev_dep_count": 7
    }
  ],
  "object_ids": [
    "VI.R01",
    "VI.R02",
    "VI.D01",
    "VI.D02",
    "VI.P01",
    "VI.L01",
    "VI.T01",
    "VI.D03",
    "VI.D04",
    "VI.D05",
    "VI.D06",
    "VI.D07",
    "VI.T02",
    "VI.D08",
    "VI.D09",
    "VI.P02",
    "VI.T03",
    "VI.T04",
    "VI.L02",
    "VI.P03",
    "VI.D10",
    "VI.D11",
    "VI.D12",
    "VI.D13",
    "VI.D14",
    "VI.L03",
    "VI.T05",
    "VI.T06",
    "VI.D15",
    "VI.D16",
    "VI.D17",
    "VI.D18",
    "VI.D19",
    "VI.D20",
    "VI.T07",
    "VI.L04",
    "VI.T08",
    "VI.T09",
    "VI.T10",
    "VI.T11",
    "VI.T12",
    "VI.T13",
    "VI.T14",
    "VI.P04",
    "VI.D21",
    "VI.D22",
    "VI.T15",
    "VI.L05",
    "VI.L06",
    "VI.P05",
    "VI.R03",
    "VI.D23",
    "VI.P06",
    "VI.P07",
    "VI.R04",
    "VI.R05",
    "VI.D24",
    "VI.D25",
    "VI.T16",
    "VI.R06",
    "VI.R07",
    "VI.D26",
    "VI.P08",
    "VI.R08",
    "VI.D27",
    "VI.T17",
    "VI.P09",
    "VI.D28",
    "VI.P10",
    "VI.R09",
    "VI.D29",
    "VI.D30",
    "VI.T18",
    "VI.R10",
    "VI.R11",
    "VI.D31",
    "VI.P11",
    "VI.D32",
    "VI.T19",
    "VI.D33",
    "VI.D34",
    "VI.P12",
    "VI.D35",
    "VI.R12",
    "VI.R13",
    "VI.D36",
    "VI.D37",
    "VI.T20",
    "VI.D38",
    "VI.P13",
    "VI.R14",
    "VI.R15",
    "VI.D39",
    "VI.T21",
    "VI.P14",
    "VI.D40",
    "VI.T22",
    "VI.P15",
    "VI.D41",
    "VI.D42",
    "VI.T23",
    "VI.R16",
    "VI.R17",
    "VI.D43",
    "VI.P16",
    "VI.D44",
    "VI.T24",
    "VI.R18",
    "VI.D45",
    "VI.P17",
    "VI.D46",
    "VI.T25",
    "VI.L07",
    "VI.D47",
    "VI.R19",
    "VI.D48",
    "VI.P18",
    "VI.D49",
    "VI.T26",
    "VI.D50",
    "VI.T27",
    "VI.R20",
    "VI.D51",
    "VI.T28",
    "VI.D52",
    "VI.P19",
    "VI.D53",
    "VI.L08",
    "VI.D54",
    "VI.D55",
    "VI.D56",
    "VI.D57",
    "VI.T29",
    "VI.D58",
    "VI.D59",
    "VI.L09",
    "VI.L10",
    "VI.T30",
    "VI.D60",
    "VI.D61",
    "VI.L11",
    "VI.T31",
    "VI.T32",
    "VI.R21",
    "VI.D62",
    "VI.D63",
    "VI.D64",
    "VI.T33",
    "VI.L12",
    "VI.D65",
    "VI.T34",
    "VI.R22",
    "VI.T35",
    "VI.T36",
    "VI.P20",
    "VI.D66",
    "VI.D67",
    "VI.T37",
    "VI.R23",
    "VI.D68",
    "VI.D69",
    "VI.T38",
    "VI.D70",
    "VI.T39",
    "VI.R24",
    "VI.L13",
    "VI.T40",
    "VI.R25",
    "VI.D71",
    "VI.D72",
    "VI.D73",
    "VI.T41",
    "VI.L14",
    "VI.T42",
    "VI.P21",
    "VI.T43",
    "VI.R26",
    "VI.D74",
    "VI.D75",
    "VI.D76",
    "VI.D77",
    "VI.L15",
    "VI.L16",
    "VI.T44",
    "VI.T45",
    "VI.T46",
    "VI.R27",
    "VI.R28",
    "VI.D78",
    "VI.D79",
    "VI.D80",
    "VI.D81",
    "VI.D82",
    "VI.D83",
    "VI.D84",
    "VI.D85",
    "VI.T47",
    "VI.T48",
    "VI.T49",
    "VI.P22",
    "VI.D87",
    "VI.D88",
    "VI.D89",
    "VI.D91",
    "VI.T52",
    "VI.P23",
    "VI.T54",
    "VI.D90",
    "VI.T53",
    "VI.P24",
    "VI.T50",
    "VI.R29",
    "VI.D86",
    "VI.T51",
    "VI.L17",
    "VI.R30",
    "VI.R31"
  ]
}